Workbook

Sheet Product
A1: Product_ID | B1: Product_Name | C1: Category | D1: Unit_Price | E1: Stock_Quantity | F1: Stock_Value | G1: Avg_Product_Price | H1: Stock_Status
A2: 1 | B2: Treadmill Pro X | C2: Gym | D2: 28000 | E2: 6 | F2: =D2*E2 -> 168000 | G2: =AVERAGE($D$2:$D$11) -> 6510 | H2: =IF(E2<10,"Reorder","Sufficient") -> Reorder
A3: 2 | B3: Garmin GPS Watch | C3: Running | D3: 8500 | E3: 25 | F3: =D3*E3 -> 212500 | G3: =AVERAGE($D$2:$D$11) -> 6510 | H3: =IF(E3<10,"Reorder","Sufficient") -> Sufficient
A4: 3 | B4: Yoga Mat Premium | C4: Gym | D4: 450 | E4: 200 | F4: =D4*E4 -> 90000 | G4: =AVERAGE($D$2:$D$11) -> 6510 | H4: =IF(E4<10,"Reorder","Sufficient") -> Sufficient
A5: 4 | B5: Trek Mountain Bike | C5: Cycling | D5: 18000 | E5: 9 | F5: =D5*E5 -> 162000 | G5: =AVERAGE($D$2:$D$11) -> 6510 | H5: =IF(E5<10,"Reorder","Sufficient") -> Reorder
A6: 5 | B6: Asics Running Shoes | C6: Running | D6: 3200 | E6: 60 | F6: =D6*E6 -> 192000 | G6: =AVERAGE($D$2:$D$11) -> 6510 | H6: =IF(E6<10,"Reorder","Sufficient") -> Sufficient
A7: 6 | B7: Speedo Swim Goggles | C7: Swimming | D7: 650 | E7: 150 | F7: =D7*E7 -> 97500 | G7: =AVERAGE($D$2:$D$11) -> 6510 | H7: =IF(E7<10,"Reorder","Sufficient") -> Sufficient
A8: 7 | B8: Adidas Football Ball | C8: Football | D8: 800 | E8: 120 | F8: =D8*E8 -> 96000 | G8: =AVERAGE($D$2:$D$11) -> 6510 | H8: =IF(E8<10,"Reorder","Sufficient") -> Sufficient
A9: 8 | B9: Nike Football Cleats | C9: Football | D9: 2500 | E9: 45 | F9: =D9*E9 -> 112500 | G9: =AVERAGE($D$2:$D$11) -> 6510 | H9: =IF(E9<10,"Reorder","Sufficient") -> Sufficient
A10: 9 | B10: Arena Swimsuit (Men) | C10: Swimming | D10: 1200 | E10: 8 | F10: =D10*E10 -> 9600 | G10: =AVERAGE($D$2:$D$11) -> 6510 | H10: =IF(E10<10,"Reorder","Sufficient") -> Reorder
A11: 10 | B11: Dumbbell Set 20 kg | C11: Gym | D11: 1800 | E11: 30 | F11: =D11*E11 -> 54000 | G11: =AVERAGE($D$2:$D$11) -> 6510 | H11: =IF(E11<10,"Reorder","Sufficient") -> Sufficient

Sheet Sales
A1: Sale_ID | B1: Product_ID | C1: Customer_ID | D1: Quantity_Sold | E1: Unit_Price | F1: Total_Sale | G1: Sale_Date | H1: Sale_Flag | I1: Category_Lookup | J1: Stock_Lookup | K1: Customer_Contact_Lookup | L1: Customer_City_Lookup | M1: Unit_Cost_Lookup | N1: Profit_Per_Sale | O1: Profit_Margin
A2: 101 | B2: 1 | C2: 1 | D2: 2 | E2: 28000 | F2: =D2*E2 -> 56000 | G2: 46027 | H2: =IF(F2>5000,"High","Normal") -> High | I2: =VLOOKUP(B2,Product!$A$2:$E$11,3,FALSE()) -> Gym | J2: =VLOOKUP(B2,Product!$A$2:$E$11,5,FALSE()) -> 6 | K2: =INDEX(Customers!$D$2:$D$50,MATCH(C2,Customers!$A$2:$A$50,0)) -> 01000000001 | L2: =INDEX(Customers!$C$2:$C$50,MATCH(C2,Customers!$A$2:$A$50,0)) -> Mansoura | M2: =IFERROR(AVERAGEIF(Purchases!$C$2:$C$50,B2,Purchases!$E$2:$E$50),0) -> 22000 | N2: =F2-(D2*M2) -> 12000 | O2: =IFERROR(N2/F2,0) -> 0.21428571
A3: 102 | B3: 3 | C3: 2 | D3: 4 | E3: 450 | F3: =D3*E3 -> 1800 | G3: 46030 | H3: =IF(F3>5000,"High","Normal") -> Normal | I3: =VLOOKUP(B3,Product!$A$2:$E$11,3,FALSE()) -> Gym | J3: =VLOOKUP(B3,Product!$A$2:$E$11,5,FALSE()) -> 200 | K3: =INDEX(Customers!$D$2:$D$50,MATCH(C3,Customers!$A$2:$A$50,0)) -> 01000000002 | L3: =INDEX(Customers!$C$2:$C$50,MATCH(C3,Customers!$A$2:$A$50,0)) -> Cairo | M3: =IFERROR(AVERAGEIF(Purchases!$C$2:$C$50,B3,Purchases!$E$2:$E$50),0) -> 280 | N3: =F3-(D3*M3) -> 680 | O3: =IFERROR(N3/F3,0) -> 0.37777778
A4: 103 | B4: 4 | C4: 3 | D4: 1 | E4: 18000 | F4: =D4*E4 -> 18000 | G4: 46034 | H4: =IF(F4>5000,"High","Normal") -> High | I4: =VLOOKUP(B4,Product!$A$2:$E$11,3,FALSE()) -> Cycling | J4: =VLOOKUP(B4,Product!$A$2:$E$11,5,FALSE()) -> 9 | K4: =INDEX(Customers!$D$2:$D$50,MATCH(C4,Customers!$A$2:$A$50,0)) -> 01000000003 | L4: =INDEX(Customers!$C$2:$C$50,MATCH(C4,Customers!$A$2:$A$50,0)) -> Mansoura | M4: =IFERROR(AVERAGEIF(Purchases!$C$2:$C$50,B4,Purchases!$E$2:$E$50),0) -> 14000 | N4: =F4-(D4*M4) -> 4000 | O4: =IFERROR(N4/F4,0) -> 0.22222222
A5: 104 | B5: 2 | C5: 1 | D5: 1 | E5: 8500 | F5: =D5*E5 -> 8500 | G5: 46056 | H5: =IF(F5>5000,"High","Normal") -> High | I5: =VLOOKUP(B5,Product!$A$2:$E$11,3,FALSE()) -> Running | J5: =VLOOKUP(B5,Product!$A$2:$E$11,5,FALSE()) -> 25 | K5: =INDEX(Customers!$D$2:$D$50,MATCH(C5,Customers!$A$2:$A$50,0)) -> 01000000001 | L5: =INDEX(Customers!$C$2:$C$50,MATCH(C5,Customers!$A$2:$A$50,0)) -> Mansoura | M5: =IFERROR(AVERAGEIF(Purchases!$C$2:$C$50,B5,Purchases!$E$2:$E$50),0) -> 6500 | N5: =F5-(D5*M5) -> 2000 | O5: =IFERROR(N5/F5,0) -> 0.23529412
A6: 105 | B6: 6 | C6: 4 | D6: 50 | E6: 650 | F6: =D6*E6 -> 32500 | G6: 46062 | H6: =IF(F6>5000,"High","Normal") -> High | I6: =VLOOKUP(B6,Product!$A$2:$E$11,3,FALSE()) -> Swimming | J6: =VLOOKUP(B6,Product!$A$2:$E$11,5,FALSE()) -> 150 | K6: =INDEX(Customers!$D$2:$D$50,MATCH(C6,Customers!$A$2:$A$50,0)) -> 01000000004 | L6: =INDEX(Customers!$C$2:$C$50,MATCH(C6,Customers!$A$2:$A$50,0)) -> Alexandria | M6: =IFERROR(AVERAGEIF(Purchases!$C$2:$C$50,B6,Purchases!$E$2:$E$50),0) -> 400 | N6: =F6-(D6*M6) -> 12500 | O6: =IFERROR(N6/F6,0) -> 0.38461538
A7: 106 | B7: 8 | C7: 5 | D7: 2 | E7: 2500 | F7: =D7*E7 -> 5000 | G7: 46071 | H7: =IF(F7>5000,"High","Normal") -> Normal | I7: =VLOOKUP(B7,Product!$A$2:$E$11,3,FALSE()) -> Football | J7: =VLOOKUP(B7,Product!$A$2:$E$11,5,FALSE()) -> 45 | K7: =INDEX(Customers!$D$2:$D$50,MATCH(C7,Customers!$A$2:$A$50,0)) -> 01000000005 | L7: =INDEX(Customers!$C$2:$C$50,MATCH(C7,Customers!$A$2:$A$50,0)) -> Cairo | M7: =IFERROR(AVERAGEIF(Purchases!$C$2:$C$50,B7,Purchases!$E$2:$E$50),0) -> 1825 | N7: =F7-(D7*M7) -> 1350 | O7: =IFERROR(N7/F7,0) -> 0.27
A8: 107 | B8: 7 | C8: 2 | D8: 6 | E8: 800 | F8: =D8*E8 -> 4800 | G8: 46082 | H8: =IF(F8>5000,"High","Normal") -> Normal | I8: =VLOOKUP(B8,Product!$A$2:$E$11,3,FALSE()) -> Football | J8: =VLOOKUP(B8,Product!$A$2:$E$11,5,FALSE()) -> 120 | K8: =INDEX(Customers!$D$2:$D$50,MATCH(C8,Customers!$A$2:$A$50,0)) -> 01000000002 | L8: =INDEX(Customers!$C$2:$C$50,MATCH(C8,Customers!$A$2:$A$50,0)) -> Cairo | M8: =IFERROR(AVERAGEIF(Purchases!$C$2:$C$50,B8,Purchases!$E$2:$E$50),0) -> 490 | N8: =F8-(D8*M8) -> 1860 | O8: =IFERROR(N8/F8,0) -> 0.3875
A9: 108 | B9: 5 | C9: 3 | D9: 1 | E9: 3200 | F9: =D9*E9 -> 3200 | G9: 46088 | H9: =IF(F9>5000,"High","Normal") -> Normal | I9: =VLOOKUP(B9,Product!$A$2:$E$11,3,FALSE()) -> Running | J9: =VLOOKUP(B9,Product!$A$2:$E$11,5,FALSE()) -> 60 | K9: =INDEX(Customers!$D$2:$D$50,MATCH(C9,Customers!$A$2:$A$50,0)) -> 01000000003 | L9: =INDEX(Customers!$C$2:$C$50,MATCH(C9,Customers!$A$2:$A$50,0)) -> Mansoura | M9: =IFERROR(AVERAGEIF(Purchases!$C$2:$C$50,B9,Purchases!$E$2:$E$50),0) -> 2300 | N9: =F9-(D9*M9) -> 900 | O9: =IFERROR(N9/F9,0) -> 0.28125
A10: 109 | B10: 10 | C10: 6 | D10: 10 | E10: 1800 | F10: =D10*E10 -> 18000 | G10: 46096 | H10: =IF(F10>5000,"High","Normal") -> High | I10: =VLOOKUP(B10,Product!$A$2:$E$11,3,FALSE()) -> Gym | J10: =VLOOKUP(B10,Product!$A$2:$E$11,5,FALSE()) -> 30 | K10: =INDEX(Customers!$D$2:$D$50,MATCH(C10,Customers!$A$2:$A$50,0)) -> 01000000006 | L10: =INDEX(Customers!$C$2:$C$50,MATCH(C10,Customers!$A$2:$A$50,0)) -> Mansoura | M10: =IFERROR(AVERAGEIF(Purchases!$C$2:$C$50,B10,Purchases!$E$2:$E$50),0) -> 1300 | N10: =F10-(D10*M10) -> 5000 | O10: =IFERROR(N10/F10,0) -> 0.27777778
A11: 110 | B11: 1 | C11: 4 | D11: 1 | E11: 28000 | F11: =D11*E11 -> 28000 | G11: 46103 | H11: =IF(F11>5000,"High","Normal") -> High | I11: =VLOOKUP(B11,Product!$A$2:$E$11,3,FALSE()) -> Gym | J11: =VLOOKUP(B11,Product!$A$2:$E$11,5,FALSE()) -> 6 | K11: =INDEX(Customers!$D$2:$D$50,MATCH(C11,Customers!$A$2:$A$50,0)) -> 01000000004 | L11: =INDEX(Customers!$C$2:$C$50,MATCH(C11,Customers!$A$2:$A$50,0)) -> Alexandria | M11: =IFERROR(AVERAGEIF(Purchases!$C$2:$C$50,B11,Purchases!$E$2:$E$50),0) -> 22000 | N11: =F11-(D11*M11) -> 6000 | O11: =IFERROR(N11/F11,0) -> 0.21428571
A12: 111 | B12: 9 | C12: 5 | D12: 3 | E12: 1200 | F12: =D12*E12 -> 3600 | G12: 46116 | H12: =IF(F12>5000,"High","Normal") -> Normal | I12: =VLOOKUP(B12,Product!$A$2:$E$11,3,FALSE()) -> Swimming | J12: =VLOOKUP(B12,Product!$A$2:$E$11,5,FALSE()) -> 8 | K12: =INDEX(Customers!$D$2:$D$50,MATCH(C12,Customers!$A$2:$A$50,0)) -> 01000000005 | L12: =INDEX(Customers!$C$2:$C$50,MATCH(C12,Customers!$A$2:$A$50,0)) -> Cairo | M12: =IFERROR(AVERAGEIF(Purchases!$C$2:$C$50,B12,Purchases!$E$2:$E$50),0) -> 850 | N12: =F12-(D12*M12) -> 1050 | O12: =IFERROR(N12/F12,0) -> 0.29166667
A13: 112 | B13: 3 | C13: 1 | D13: 2 | E13: 450 | F13: =D13*E13 -> 900 | G13: 46123 | H13: =IF(F13>5000,"High","Normal") -> Normal | I13: =VLOOKUP(B13,Product!$A$2:$E$11,3,FALSE()) -> Gym | J13: =VLOOKUP(B13,Product!$A$2:$E$11,5,FALSE()) -> 200 | K13: =INDEX(Customers!$D$2:$D$50,MATCH(C13,Customers!$A$2:$A$50,0)) -> 01000000001 | L13: =INDEX(Customers!$C$2:$C$50,MATCH(C13,Customers!$A$2:$A$50,0)) -> Mansoura | M13: =IFERROR(AVERAGEIF(Purchases!$C$2:$C$50,B13,Purchases!$E$2:$E$50),0) -> 280 | N13: =F13-(D13*M13) -> 340 | O13: =IFERROR(N13/F13,0) -> 0.37777778
... A21: 120 | B21: 5 | C21: 2 | D21: 1 | E21: 3200 | F21: =D21*E21 -> 3200 | G21: 46201 | H21: =IF(F21>5000,"High","Normal") -> Normal | I21: =VLOOKUP(B21,Product!$A$2:$E$11,3,FALSE()) -> Running | J21: =VLOOKUP(B21,Product!$A$2:$E$11,5,FALSE()) -> 60 | K21: =INDEX(Customers!$D$2:$D$50,MATCH(C21,Customers!$A$2:$A$50,0)) -> 01000000002 | L21: =INDEX(Customers!$C$2:$C$50,MATCH(C21,Customers!$A$2:$A$50,0)) -> Cairo | M21: =IFERROR(AVERAGEIF(Purchases!$C$2:$C$50,B21,Purchases!$E$2:$E$50),0) -> 2300 | N21: =F21-(D21*M21) -> 900 | O21: =IFERROR(N21/F21,0) -> 0.28125

Sheet Customers
A1: Customer_ID | B1: Customer_Name | C1: City | D1: Contact_Number | E1: Total_Purchases | F1: Loyalty | G1: Customer_Rank
A2: 1 | B2: Mohamed Elsaeed | C2: Mansoura | D2: 01000000001 | E2: =SUMIF(Sales!$C$2:$C$50,A2,Sales!$F$2:$F$50) -> 74400 | F2: =IF(E2>10000,"Loyal","Regular") -> Loyal | G2: =RANK(E2,$E$2:$E$7,0) -> 2
A3: 2 | B3: Ahmed Hassan | C3: Cairo | D3: 01000000002 | E3: =SUMIF(Sales!$C$2:$C$50,A3,Sales!$F$2:$F$50) -> 27800 | F3: =IF(E3>10000,"Loyal","Regular") -> Loyal | G3: =RANK(E3,$E$2:$E$7,0) -> 6
A4: 3 | B4: Omar Mostafa | C4: Mansoura | D4: 01000000003 | E4: =SUMIF(Sales!$C$2:$C$50,A4,Sales!$F$2:$F$50) -> 37450 | F4: =IF(E4>10000,"Loyal","Regular") -> Loyal | G4: =RANK(E4,$E$2:$E$7,0) -> 5
A5: 4 | B5: Yasmin Adel | C5: Alexandria | D5: 01000000004 | E5: =SUMIF(Sales!$C$2:$C$50,A5,Sales!$F$2:$F$50) -> 62900 | F5: =IF(E5>10000,"Loyal","Regular") -> Loyal | G5: =RANK(E5,$E$2:$E$7,0) -> 3
A6: 5 | B6: Karim Said | C6: Cairo | D6: 01000000005 | E6: =SUMIF(Sales!$C$2:$C$50,A6,Sales!$F$2:$F$50) -> 92600 | F6: =IF(E6>10000,"Loyal","Regular") -> Loyal | G6: =RANK(E6,$E$2:$E$7,0) -> 1
A7: 6 | B7: Nada Tarek | C7: Mansoura | D7: 01000000006 | E7: =SUMIF(Sales!$C$2:$C$50,A7,Sales!$F$2:$F$50) -> 37500 | F7: =IF(E7>10000,"Loyal","Regular") -> Loyal | G7: =RANK(E7,$E$2:$E$7,0) -> 4

Sheet Purchases
A1: Purchase_ID | B1: Supplier_Name | C1: Product_ID | D1: Quantity_Purchased | E1: Unit_Cost | F1: Total_Cost | G1: Purchase_Date | H1: Order_Type | I1: Category_Lookup
A2: 201 | B2: Adidas Egypt | C2: 7 | D2: 300 | E2: 500 | F2: =D2*E2 -> 150000 | G2: 45992 | H2: =IF(F2>10000,"Bulk","Normal") -> Bulk | I2: =VLOOKUP(C2,Product!$A$2:$C$11,3,FALSE()) -> Football
A3: 202 | B3: Nike ME | C3: 8 | D3: 100 | E3: 1800 | F3: =D3*E3 -> 180000 | G3: 45996 | H3: =IF(F3>10000,"Bulk","Normal") -> Bulk | I3: =VLOOKUP(C3,Product!$A$2:$C$11,3,FALSE()) -> Football
A4: 203 | B4: FitnessPro Imports | C4: 1 | D4: 10 | E4: 22000 | F4: =D4*E4 -> 220000 | G4: 46001 | H4: =IF(F4>10000,"Bulk","Normal") -> Bulk | I4: =VLOOKUP(C4,Product!$A$2:$C$11,3,FALSE()) -> Gym
A5: 204 | B5: FitnessPro Imports | C5: 10 | D5: 80 | E5: 1300 | F5: =D5*E5 -> 104000 | G5: 46006 | H5: =IF(F5>10000,"Bulk","Normal") -> Bulk | I5: =VLOOKUP(C5,Product!$A$2:$C$11,3,FALSE()) -> Gym
A6: 205 | B6: Decathlon Egypt | C6: 3 | D6: 500 | E6: 280 | F6: =D6*E6 -> 140000 | G6: 46009 | H6: =IF(F6>10000,"Bulk","Normal") -> Bulk | I6: =VLOOKUP(C6,Product!$A$2:$C$11,3,FALSE()) -> Gym
A7: 206 | B7: Decathlon Egypt | C7: 6 | D7: 400 | E7: 400 | F7: =D7*E7 -> 160000 | G7: 46013 | H7: =IF(F7>10000,"Bulk","Normal") -> Bulk | I7: =VLOOKUP(C7,Product!$A$2:$C$11,3,FALSE()) -> Swimming
A8: 207 | B8: Garmin Distributor | C8: 2 | D8: 40 | E8: 6500 | F8: =D8*E8 -> 260000 | G8: 46027 | H8: =IF(F8>10000,"Bulk","Normal") -> Bulk | I8: =VLOOKUP(C8,Product!$A$2:$C$11,3,FALSE()) -> Running
A9: 208 | B9: Trek Bicycles | C9: 4 | D9: 15 | E9: 14000 | F9: =D9*E9 -> 210000 | G9: 46034 | H9: =IF(F9>10000,"Bulk","Normal") -> Bulk | I9: =VLOOKUP(C9,Product!$A$2:$C$11,3,FALSE()) -> Cycling
A10: 209 | B10: FitnessPro Imports | C10: 5 | D10: 80 | E10: 2300 | F10: =D10*E10 -> 184000 | G10: 46040 | H10: =IF(F10>10000,"Bulk","Normal") -> Bulk | I10: =VLOOKUP(C10,Product!$A$2:$C$11,3,FALSE()) -> Running
A11: 210 | B11: Decathlon Egypt | C11: 9 | D11: 30 | E11: 850 | F11: =D11*E11 -> 25500 | G11: 46055 | H11: =IF(F11>10000,"Bulk","Normal") -> Bulk | I11: =VLOOKUP(C11,Product!$A$2:$C$11,3,FALSE()) -> Swimming
A12: 211 | B12: Adidas Egypt | C12: 7 | D12: 200 | E12: 480 | F12: =D12*E12 -> 96000 | G12: 46067 | H12: =IF(F12>10000,"Bulk","Normal") -> Bulk | I12: =VLOOKUP(C12,Product!$A$2:$C$11,3,FALSE()) -> Football
A13: 212 | B13: Nike ME | C13: 8 | D13: 50 | E13: 1850 | F13: =D13*E13 -> 92500 | G13: 46084 | H13: =IF(F13>10000,"Bulk","Normal") -> Bulk | I13: =VLOOKUP(C13,Product!$A$2:$C$11,3,FALSE()) -> Football

Sheet Expenses
A1: Expense_ID | B1: Expense_Type | C1: Amount | D1: Date | E1: Notes | F1: Flag | G1: Essential | H1: After_Cut_10pct
A2: 301 | B2: Rent | C2: 12000 | D2: 46023 | E2: Shop monthly rent | F2: =IF(C2>2000,"Check","OK") -> Check | G2: Yes | H2: =IF(G2="No",C2*0.9,C2) -> 12000
A3: 302 | B3: Salaries | C3: 22000 | D3: 46027 | E3: Monthly payroll | F3: =IF(C3>2000,"Check","OK") -> Check | G3: Yes | H3: =IF(G3="No",C3*0.9,C3) -> 22000
A4: 303 | B4: Electricity | C4: 3000 | D4: 46032 | E4: Utility | F4: =IF(C4>2000,"Check","OK") -> Check | G4: Yes | H4: =IF(G4="No",C4*0.9,C4) -> 3000
A5: 304 | B5: Marketing | C5: 3500 | D5: 46037 | E5: Facebook ads | F5: =IF(C5>2000,"Check","OK") -> Check | G5: No | H5: =IF(G5="No",C5*0.9,C5) -> 3150
A6: 305 | B6: Cleaning | C6: 800 | D6: 46042 | E6: Cleaning service | F6: =IF(C6>2000,"Check","OK") -> OK | G6: Yes | H6: =IF(G6="No",C6*0.9,C6) -> 800
A7: 306 | B7: Rent | C7: 12000 | D7: 46054 | E7: Shop monthly rent | F7: =IF(C7>2000,"Check","OK") -> Check | G7: Yes | H7: =IF(G7="No",C7*0.9,C7) -> 12000
A8: 307 | B8: Salaries | C8: 22000 | D8: 46058 | E8: Monthly payroll | F8: =IF(C8>2000,"Check","OK") -> Check | G8: Yes | H8: =IF(G8="No",C8*0.9,C8) -> 22000
A9: 308 | B9: Marketing | C9: 5500 | D9: 46068 | E9: Google ads (high) | F9: =IF(C9>2000,"Check","OK") -> Check | G9: No | H9: =IF(G9="No",C9*0.9,C9) -> 4950
A10: 309 | B10: Maintenance | C10: 2200 | D10: 46075 | E10: Treadmill servicing | F10: =IF(C10>2000,"Check","OK") -> Check | G10: Yes | H10: =IF(G10="No",C10*0.9,C10) -> 2200
A11: 310 | B11: Cleaning | C11: 800 | D11: 46078 | E11: Cleaning service | F11: =IF(C11>2000,"Check","OK") -> OK | G11: Yes | H11: =IF(G11="No",C11*0.9,C11) -> 800
A12: 311 | B12: Rent | C12: 12000 | D12: 46082 | E12: Shop monthly rent | F12: =IF(C12>2000,"Check","OK") -> Check | G12: Yes | H12: =IF(G12="No",C12*0.9,C12) -> 12000
A13: 312 | B13: Salaries | C13: 22000 | D13: 46086 | E13: Monthly payroll | F13: =IF(C13>2000,"Check","OK") -> Check | G13: Yes | H13: =IF(G13="No",C13*0.9,C13) -> 22000
... A16: 315 | B16: Office | C16: 900 | D16: 46101 | E16: Stationery | F16: =IF(C16>2000,"Check","OK") -> OK | G16: No | H16: =IF(G16="No",C16*0.9,C16) -> 810

Sheet Analysis
A1: Advanced analysis (Task 2 – Part 1)
A3: Supplier | B3: Total Purchase Cost (SUMIF) | C3: Avg Quantity Purchased (AVERAGEIF)
A4: Adidas Egypt | B4: =SUMIF(Purchases!$B$2:$B$50,"Adidas Egypt",Purchases!$F$2:$F$50) -> 246000 | C4: =IFERROR(AVERAGEIF(Purchases!$B$2:$B$50,"Adidas Egypt",Purchases!$D$2:$D$50),0) -> 250
A5: Nike ME | B5: =SUMIF(Purchases!$B$2:$B$50,"Nike ME",Purchases!$F$2:$F$50) -> 272500 | C5: =IFERROR(AVERAGEIF(Purchases!$B$2:$B$50,"Nike ME",Purchases!$D$2:$D$50),0) -> 75
A6: FitnessPro Imports | B6: =SUMIF(Purchases!$B$2:$B$50,"FitnessPro Imports",Purchases!$F$2:$F$50) -> 508000 | C6: =IFERROR(AVERAGEIF(Purchases!$B$2:$B$50,"FitnessPro Imports",Purchases!$D$2:$D$50),0) -> 56.666667
A7: Decathlon Egypt | B7: =SUMIF(Purchases!$B$2:$B$50,"Decathlon Egypt",Purchases!$F$2:$F$50) -> 325500 | C7: =IFERROR(AVERAGEIF(Purchases!$B$2:$B$50,"Decathlon Egypt",Purchases!$D$2:$D$50),0) -> 310
A8: Garmin Distributor | B8: =SUMIF(Purchases!$B$2:$B$50,"Garmin Distributor",Purchases!$F$2:$F$50) -> 260000 | C8: =IFERROR(AVERAGEIF(Purchases!$B$2:$B$50,"Garmin Distributor",Purchases!$D$2:$D$50),0) -> 40
A9: Trek Bicycles | B9: =SUMIF(Purchases!$B$2:$B$50,"Trek Bicycles",Purchases!$F$2:$F$50) -> 210000 | C9: =IFERROR(AVERAGEIF(Purchases!$B$2:$B$50,"Trek Bicycles",Purchases!$D$2:$D$50),0) -> 15
A12: Product_ID | B12: Product_Name | C12: Initial_Stock | D12: Sold (SUMIF) | E12: Remaining_Stock | F12: Profit_Per_Product | G12: Profit_Status
A13: 1 | B13: Treadmill Pro X | C13: =VLOOKUP(A13,Product!$A$2:$E$11,5,FALSE()) -> 6 | D13: =SUMIF(Sales!$B$2:$B$50,A13,Sales!$D$2:$D$50) -> 6 | E13: =C13-D13 -> 0 | F13: =SUMIF(Sales!$B$2:$B$50,A13,Sales!$N$2:$N$50) -> 36000 | G13: =IF(F13<0,"Negative","Positive") -> Positive
A14: 2 | B14: Garmin GPS Watch | C14: =VLOOKUP(A14,Product!$A$2:$E$11,5,FALSE()) -> 25 | D14: =SUMIF(Sales!$B$2:$B$50,A14,Sales!$D$2:$D$50) -> 3 | E14: =C14-D14 -> 22 | F14: =SUMIF(Sales!$B$2:$B$50,A14,Sales!$N$2:$N$50) -> 6000 | G14: =IF(F14<0,"Negative","Positive") -> Positive
A15: 3 | B15: Yoga Mat Premium | C15: =VLOOKUP(A15,Product!$A$2:$E$11,5,FALSE()) -> 200 | D15: =SUMIF(Sales!$B$2:$B$50,A15,Sales!$D$2:$D$50) -> 6 | E15: =C15-D15 -> 194 | F15: =SUMIF(Sales!$B$2:$B$50,A15,Sales!$N$2:$N$50) -> 1020 | G15: =IF(F15<0,"Negative","Positive") -> Positive
A16: 4 | B16: Trek Mountain Bike | C16: =VLOOKUP(A16,Product!$A$2:$E$11,5,FALSE()) -> 9 | D16: =SUMIF(Sales!$B$2:$B$50,A16,Sales!$D$2:$D$50) -> 2 | E16: =C16-D16 -> 7 | F16: =SUMIF(Sales!$B$2:$B$50,A16,Sales!$N$2:$N$50) -> 8000 | G16: =IF(F16<0,"Negative","Positive") -> Positive
A17: 5 | B17: Asics Running Shoes | C17: =VLOOKUP(A17,Product!$A$2:$E$11,5,FALSE()) -> 60 | D17: =SUMIF(Sales!$B$2:$B$50,A17,Sales!$D$2:$D$50) -> 2 | E17: =C17-D17 -> 58 | F17: =SUMIF(Sales!$B$2:$B$50,A17,Sales!$N$2:$N$50) -> 1800 | G17: =IF(F17<0,"Negative","Positive") -> Positive
A18: 6 | B18: Speedo Swim Goggles | C18: =VLOOKUP(A18,Product!$A$2:$E$11,5,FALSE()) -> 150 | D18: =SUMIF(Sales!$B$2:$B$50,A18,Sales!$D$2:$D$50) -> 75 | E18: =C18-D18 -> 75 | F18: =SUMIF(Sales!$B$2:$B$50,A18,Sales!$N$2:$N$50) -> 18750 | G18: =IF(F18<0,"Negative","Positive") -> Positive
A19: 7 | B19: Adidas Football Ball | C19: =VLOOKUP(A19,Product!$A$2:$E$11,5,FALSE()) -> 120 | D19: =SUMIF(Sales!$B$2:$B$50,A19,Sales!$D$2:$D$50) -> 9 | E19: =C19-D19 -> 111 | F19: =SUMIF(Sales!$B$2:$B$50,A19,Sales!$N$2:$N$50) -> 2790 | G19: =IF(F19<0,"Negative","Positive") -> Positive
A20: 8 | B20: Nike Football Cleats | C20: =VLOOKUP(A20,Product!$A$2:$E$11,5,FALSE()) -> 45 | D20: =SUMIF(Sales!$B$2:$B$50,A20,Sales!$D$2:$D$50) -> 3 | E20: =C20-D20 -> 42 | F20: =SUMIF(Sales!$B$2:$B$50,A20,Sales!$N$2:$N$50) -> 2025 | G20: =IF(F20<0,"Negative","Positive") -> Positive
A21: 9 | B21: Arena Swimsuit (Men) | C21: =VLOOKUP(A21,Product!$A$2:$E$11,5,FALSE()) -> 8 | D21: =SUMIF(Sales!$B$2:$B$50,A21,Sales!$D$2:$D$50) -> 3 | E21: =C21-D21 -> 5 | F21: =SUMIF(Sales!$B$2:$B$50,A21,Sales!$N$2:$N$50) -> 1050 | G21: =IF(F21<0,"Negative","Positive") -> Positive
A22: 10 | B22: Dumbbell Set 20 kg | C22: =VLOOKUP(A22,Product!$A$2:$E$11,5,FALSE()) -> 30 | D22: =SUMIF(Sales!$B$2:$B$50,A22,Sales!$D$2:$D$50) -> 15 | E22: =C22-D22 -> 15 | F22: =SUMIF(Sales!$B$2:$B$50,A22,Sales!$N$2:$N$50) -> 7500 | G22: =IF(F22<0,"Negative","Positive") -> Positive
A25: Top 5 Customers (by Total_Purchases)
A26: Rank | B26: Customer_Name | C26: Total_Purchases
A27: 1 | B27: =INDEX(Customers!$B$2:$B$10,MATCH(1,Customers!$G$2:$G$10,0)) -> Karim Said | C27: =INDEX(Customers!$E$2:$E$10,MATCH(1,Customers!$G$2:$G$10,0)) -> 92600
A28: 2 | B28: =INDEX(Customers!$B$2:$B$10,MATCH(2,Customers!$G$2:$G$10,0)) -> Mohamed Elsaeed | C28: =INDEX(Customers!$E$2:$E$10,MATCH(2,Customers!$G$2:$G$10,0)) -> 74400
A29: 3 | B29: =INDEX(Customers!$B$2:$B$10,MATCH(3,Customers!$G$2:$G$10,0)) -> Yasmin Adel | C29: =INDEX(Customers!$E$2:$E$10,MATCH(3,Customers!$G$2:$G$10,0)) -> 62900
A30: 4 | B30: =INDEX(Customers!$B$2:$B$10,MATCH(4,Customers!$G$2:$G$10,0)) -> Nada Tarek | C30: =INDEX(Customers!$E$2:$E$10,MATCH(4,Customers!$G$2:$G$10,0)) -> 37500
A31: 5 | B31: =INDEX(Customers!$B$2:$B$10,MATCH(5,Customers!$G$2:$G$10,0)) -> Omar Mostafa | C31: =INDEX(Customers!$E$2:$E$10,MATCH(5,Customers!$G$2:$G$10,0)) -> 37450

Sheet WhatIf
A1: What-If / Scenario Analysis (Task 2 – Part 2)
A3: 1) Product stock drops by 20% — impact on Total Stock Value
A4: Product_ID | B4: Stock_Original | C4: Stock_After_Drop_20pct | D4: Unit_Price | E4: Stock_Value_New
A5: 1 | B5: =VLOOKUP(A5,Product!$A$2:$E$11,5,FALSE()) -> 6 | C5: =B5*0.8 -> 4.8 | D5: =VLOOKUP(A5,Product!$A$2:$E$11,4,FALSE()) -> 28000 | E5: =C5*D5 -> 134400
A6: 2 | B6: =VLOOKUP(A6,Product!$A$2:$E$11,5,FALSE()) -> 25 | C6: =B6*0.8 -> 20 | D6: =VLOOKUP(A6,Product!$A$2:$E$11,4,FALSE()) -> 8500 | E6: =C6*D6 -> 170000
A7: 3 | B7: =VLOOKUP(A7,Product!$A$2:$E$11,5,FALSE()) -> 200 | C7: =B7*0.8 -> 160 | D7: =VLOOKUP(A7,Product!$A$2:$E$11,4,FALSE()) -> 450 | E7: =C7*D7 -> 72000
A8: 4 | B8: =VLOOKUP(A8,Product!$A$2:$E$11,5,FALSE()) -> 9 | C8: =B8*0.8 -> 7.2 | D8: =VLOOKUP(A8,Product!$A$2:$E$11,4,FALSE()) -> 18000 | E8: =C8*D8 -> 129600
A9: 5 | B9: =VLOOKUP(A9,Product!$A$2:$E$11,5,FALSE()) -> 60 | C9: =B9*0.8 -> 48 | D9: =VLOOKUP(A9,Product!$A$2:$E$11,4,FALSE()) -> 3200 | E9: =C9*D9 -> 153600
A10: 6 | B10: =VLOOKUP(A10,Product!$A$2:$E$11,5,FALSE()) -> 150 | C10: =B10*0.8 -> 120 | D10: =VLOOKUP(A10,Product!$A$2:$E$11,4,FALSE()) -> 650 | E10: =C10*D10 -> 78000
A11: 7 | B11: =VLOOKUP(A11,Product!$A$2:$E$11,5,FALSE()) -> 120 | C11: =B11*0.8 -> 96 | D11: =VLOOKUP(A11,Product!$A$2:$E$11,4,FALSE()) -> 800 | E11: =C11*D11 -> 76800
A12: 8 | B12: =VLOOKUP(A12,Product!$A$2:$E$11,5,FALSE()) -> 45 | C12: =B12*0.8 -> 36 | D12: =VLOOKUP(A12,Product!$A$2:$E$11,4,FALSE()) -> 2500 | E12: =C12*D12 -> 90000
A13: 9 | B13: =VLOOKUP(A13,Product!$A$2:$E$11,5,FALSE()) -> 8 | C13: =B13*0.8 -> 6.4 | D13: =VLOOKUP(A13,Product!$A$2:$E$11,4,FALSE()) -> 1200 | E13: =C13*D13 -> 7680
A14: 10 | B14: =VLOOKUP(A14,Product!$A$2:$E$11,5,FALSE()) -> 30 | C14: =B14*0.8 -> 24 | D14: =VLOOKUP(A14,Product!$A$2:$E$11,4,FALSE()) -> 1800 | E14: =C14*D14 -> 43200
D15: Total New Stock Value: | E15: =SUM(E5:E14) -> 955280
A18: 2) Top-3 products price change — new Total Sales
A19: Product_ID | B19: Current Total Sales | C19: +5% Scenario | D19: +10% Scenario | E19: +15% Scenario
A20: 1 | B20: =SUMIF(Sales!$B$2:$B$50,A20,Sales!$F$2:$F$50) -> 168000 | C20: =B20*1.05 -> 176400 | D20: =B20*1.1 -> 184800 | E20: =B20*1.15 -> 193200
A21: 4 | B21: =SUMIF(Sales!$B$2:$B$50,A21,Sales!$F$2:$F$50) -> 36000 | C21: =B21*1.05 -> 37800 | D21: =B21*1.1 -> 39600 | E21: =B21*1.15 -> 41400
A22: 5 | B22: =SUMIF(Sales!$B$2:$B$50,A22,Sales!$F$2:$F$50) -> 6400 | C22: =B22*1.05 -> 6720 | D22: =B22*1.1 -> 7040 | E22: =B22*1.15 -> 7360
A24: 3) Add 3 new customers in Cairo — impact on city counts
A25: City | B25: Current Customer Count | C25: After Adding 3 in Cairo
A26: Mansoura | B26: =COUNTIF(Customers!$C$2:$C$10,"Mansoura") -> 3 | C26: =B26+IF(A26="Cairo",3,0) -> 3
A27: Cairo | B27: =COUNTIF(Customers!$C$2:$C$10,"Cairo") -> 2 | C27: =B27+IF(A27="Cairo",3,0) -> 5
A28: Alex | B28: =COUNTIF(Customers!$C$2:$C$10,"Alex") -> 0 | C28: =B28+IF(A28="Cairo",3,0) -> 0
A30: 4) FitnessPro Imports unit cost +10% — Total Purchases impact
A31: Current Total (FitnessPro Imports) | B31: =SUMIF(Purchases!$B$2:$B$50,"FitnessPro Imports",Purchases!$F$2:$F$50) -> 508000
A32: After +10% | B32: =B31*1.1 -> 558800
A33: Difference | B33: =B32-B31 -> 50800
A35: 5) Cut 10% of non-essential expenses
A36: Total Expenses (current) | B36: =SUM(Expenses!C2:C50) -> 123000
A37: Total Expenses (after cut) | B37: =SUM(Expenses!H2:H50) -> 121860
A38: Savings | B38: =B36-B37 -> 1140

Sheet GoalSeek
A1: Goal Seek tasks (Task 2 – Part 3)
A3: # | B3: Goal | C3: Set cell | D3: To value | E3: By changing cell
A4: 1 | B4: Make a Regular customer become Loyal | C4: Customers!E2 (Total_Purchases of customer 1) | D4: 10001 | E4: An adjustable Sales!F<row> for that customer
A5: 2 | B5: Reach Profit_Per_Sale of 1500 for a chosen sale | C5: Sales!N5 (Profit_Per_Sale) | D5: 1500 | E5: Sales!E5 (Unit_Price)
A6: 3 | B6: Keep a purchase within budget 50,000 | C6: Purchases!F2 (Total_Cost) | D6: 50000 | E6: Purchases!E2 (Unit_Cost)
A7: 4 | B7: Total expenses ≤ 70,000 | C7: B1 below (=SUM(Expenses!C2:C50)) | D7: 70000 | E7: Expenses!C4 (Marketing amount)
A8: 5 | B8: Stock_Value of product 1 = 60,000 without changing quantity | C8: Product!F2 (Stock_Value of product 1) | D8: 60000 | E8: Product!D2 (Unit_Price of product 1)
A11: Live cell to use for Goal Seek #4 (Set cell): | B11: =SUM(Expenses!C2:C50) -> 123000
A13: How to run Goal Seek in Excel:
A14: 1. Open the workbook in Excel.
A15: 2. Click the cell listed under 'Set cell'.
A16: 3. Go to: Data → What-If Analysis → Goal Seek.
A17: 4. Set cell = (the cell), To value = (target), By changing cell = (the input cell).
A18: 5. Click OK and screenshot the dialog + the result.

Sheet Pivots
A1: Pivot-style summaries (Task 2 – Part 4)
A2: Real PivotTables/PivotCharts require Microsoft Excel. The tables below reproduce the same numbers using SUMIF/SUMIFS so you can verify or compare to your own Pivots.
A4: 1) Profit per Product Category
A5: Category | B5: Total_Sale | C5: Total_Profit | D5: Profit_Margin_%
A6: Football | B6: =SUMIFS(Sales!$F$2:$F$50,Sales!$I$2:$I$50,"Football") -> 14700 | C6: =SUMIFS(Sales!$N$2:$N$50,Sales!$I$2:$I$50,"Football") -> 4815 | D6: =IFERROR(C6/B6,0) -> 0.32755102
A7: Gym | B7: =SUMIFS(Sales!$F$2:$F$50,Sales!$I$2:$I$50,"Gym") -> 197700 | C7: =SUMIFS(Sales!$N$2:$N$50,Sales!$I$2:$I$50,"Gym") -> 44520 | D7: =IFERROR(C7/B7,0) -> 0.22518968
A8: Swimming | B8: =SUMIFS(Sales!$F$2:$F$50,Sales!$I$2:$I$50,"Swimming") -> 52350 | C8: =SUMIFS(Sales!$N$2:$N$50,Sales!$I$2:$I$50,"Swimming") -> 19800 | D8: =IFERROR(C8/B8,0) -> 0.3782235
A9: Running | B9: =SUMIFS(Sales!$F$2:$F$50,Sales!$I$2:$I$50,"Running") -> 31900 | C9: =SUMIFS(Sales!$N$2:$N$50,Sales!$I$2:$I$50,"Running") -> 7800 | D9: =IFERROR(C9/B9,0) -> 0.24451411
A10: Cycling | B10: =SUMIFS(Sales!$F$2:$F$50,Sales!$I$2:$I$50,"Cycling") -> 36000 | C10: =SUMIFS(Sales!$N$2:$N$50,Sales!$I$2:$I$50,"Cycling") -> 8000 | D10: =IFERROR(C10/B10,0) -> 0.22222222
A12: 2) Monthly Sales (Total_Sale) — rows = Product, cols = Month
A13: Product_ID | B13: Product_Name | C13: M1 | D13: M2 | E13: M3 | F13: M4 | G13: M5 | H13: M6
A14: 1 | B14: Treadmill Pro X | C14: =SUMPRODUCT((Sales!$B$2:$B$50=1)*(MONTH(Sales!$G$2:$G$50)=1)*Sales!$F$2:$F$50) -> 56000 | D14: =SUMPRODUCT((Sales!$B$2:$B$50=1)*(MONTH(Sales!$G$2:$G$50)=2)*Sales!$F$2:$F$50) -> 0 | E14: =SUMPRODUCT((Sales!$B$2:$B$50=1)*(MONTH(Sales!$G$2:$G$50)=3)*Sales!$F$2:$F$50) -> 28000 | F14: =SUMPRODUCT((Sales!$B$2:$B$50=1)*(MONTH(Sales!$G$2:$G$50)=4)*Sales!$F$2:$F$50) -> 0 | G14: =SUMPRODUCT((Sales!$B$2:$B$50=1)*(MONTH(Sales!$G$2:$G$50)=5)*Sales!$F$2:$F$50) -> 0 | H14: =SUMPRODUCT((Sales!$B$2:$B$50=1)*(MONTH(Sales!$G$2:$G$50)=6)*Sales!$F$2:$F$50) -> 84000
A15: 2 | B15: Garmin GPS Watch | C15: =SUMPRODUCT((Sales!$B$2:$B$50=2)*(MONTH(Sales!$G$2:$G$50)=1)*Sales!$F$2:$F$50) -> 0 | D15: =SUMPRODUCT((Sales!$B$2:$B$50=2)*(MONTH(Sales!$G$2:$G$50)=2)*Sales!$F$2:$F$50) -> 8500 | E15: =SUMPRODUCT((Sales!$B$2:$B$50=2)*(MONTH(Sales!$G$2:$G$50)=3)*Sales!$F$2:$F$50) -> 0 | F15: =SUMPRODUCT((Sales!$B$2:$B$50=2)*(MONTH(Sales!$G$2:$G$50)=4)*Sales!$F$2:$F$50) -> 0 | G15: =SUMPRODUCT((Sales!$B$2:$B$50=2)*(MONTH(Sales!$G$2:$G$50)=5)*Sales!$F$2:$F$50) -> 0 | H15: =SUMPRODUCT((Sales!$B$2:$B$50=2)*(MONTH(Sales!$G$2:$G$50)=6)*Sales!$F$2:$F$50) -> 17000
A16: 3 | B16: Yoga Mat Premium | C16: =SUMPRODUCT((Sales!$B$2:$B$50=3)*(MONTH(Sales!$G$2:$G$50)=1)*Sales!$F$2:$F$50) -> 1800 | D16: =SUMPRODUCT((Sales!$B$2:$B$50=3)*(MONTH(Sales!$G$2:$G$50)=2)*Sales!$F$2:$F$50) -> 0 | E16: =SUMPRODUCT((Sales!$B$2:$B$50=3)*(MONTH(Sales!$G$2:$G$50)=3)*Sales!$F$2:$F$50) -> 0 | F16: =SUMPRODUCT((Sales!$B$2:$B$50=3)*(MONTH(Sales!$G$2:$G$50)=4)*Sales!$F$2:$F$50) -> 900 | G16: =SUMPRODUCT((Sales!$B$2:$B$50=3)*(MONTH(Sales!$G$2:$G$50)=5)*Sales!$F$2:$F$50) -> 0 | H16: =SUMPRODUCT((Sales!$B$2:$B$50=3)*(MONTH(Sales!$G$2:$G$50)=6)*Sales!$F$2:$F$50) -> 0
A17: 4 | B17: Trek Mountain Bike | C17: =SUMPRODUCT((Sales!$B$2:$B$50=4)*(MONTH(Sales!$G$2:$G$50)=1)*Sales!$F$2:$F$50) -> 18000 | D17: =SUMPRODUCT((Sales!$B$2:$B$50=4)*(MONTH(Sales!$G$2:$G$50)=2)*Sales!$F$2:$F$50) -> 0 | E17: =SUMPRODUCT((Sales!$B$2:$B$50=4)*(MONTH(Sales!$G$2:$G$50)=3)*Sales!$F$2:$F$50) -> 0 | F17: =SUMPRODUCT((Sales!$B$2:$B$50=4)*(MONTH(Sales!$G$2:$G$50)=4)*Sales!$F$2:$F$50) -> 18000 | G17: =SUMPRODUCT((Sales!$B$2:$B$50=4)*(MONTH(Sales!$G$2:$G$50)=5)*Sales!$F$2:$F$50) -> 0 | H17: =SUMPRODUCT((Sales!$B$2:$B$50=4)*(MONTH(Sales!$G$2:$G$50)=6)*Sales!$F$2:$F$50) -> 0
A18: 5 | B18: Asics Running Shoes | C18: =SUMPRODUCT((Sales!$B$2:$B$50=5)*(MONTH(Sales!$G$2:$G$50)=1)*Sales!$F$2:$F$50) -> 0 | D18: =SUMPRODUCT((Sales!$B$2:$B$50=5)*(MONTH(Sales!$G$2:$G$50)=2)*Sales!$F$2:$F$50) -> 0 | E18: =SUMPRODUCT((Sales!$B$2:$B$50=5)*(MONTH(Sales!$G$2:$G$50)=3)*Sales!$F$2:$F$50) -> 3200 | F18: =SUMPRODUCT((Sales!$B$2:$B$50=5)*(MONTH(Sales!$G$2:$G$50)=4)*Sales!$F$2:$F$50) -> 0 | G18: =SUMPRODUCT((Sales!$B$2:$B$50=5)*(MONTH(Sales!$G$2:$G$50)=5)*Sales!$F$2:$F$50) -> 0 | H18: =SUMPRODUCT((Sales!$B$2:$B$50=5)*(MONTH(Sales!$G$2:$G$50)=6)*Sales!$F$2:$F$50) -> 3200
A19: 6 | B19: Speedo Swim Goggles | C19: =SUMPRODUCT((Sales!$B$2:$B$50=6)*(MONTH(Sales!$G$2:$G$50)=1)*Sales!$F$2:$F$50) -> 0 | D19: =SUMPRODUCT((Sales!$B$2:$B$50=6)*(MONTH(Sales!$G$2:$G$50)=2)*Sales!$F$2:$F$50) -> 32500 | E19: =SUMPRODUCT((Sales!$B$2:$B$50=6)*(MONTH(Sales!$G$2:$G$50)=3)*Sales!$F$2:$F$50) -> 0 | F19: =SUMPRODUCT((Sales!$B$2:$B$50=6)*(MONTH(Sales!$G$2:$G$50)=4)*Sales!$F$2:$F$50) -> 0 | G19: =SUMPRODUCT((Sales!$B$2:$B$50=6)*(MONTH(Sales!$G$2:$G$50)=5)*Sales!$F$2:$F$50) -> 16250 | H19: =SUMPRODUCT((Sales!$B$2:$B$50=6)*(MONTH(Sales!$G$2:$G$50)=6)*Sales!$F$2:$F$50) -> 0
A20: 7 | B20: Adidas Football Ball | C20: =SUMPRODUCT((Sales!$B$2:$B$50=7)*(MONTH(Sales!$G$2:$G$50)=1)*Sales!$F$2:$F$50) -> 0 | D20: =SUMPRODUCT((Sales!$B$2:$B$50=7)*(MONTH(Sales!$G$2:$G$50)=2)*Sales!$F$2:$F$50) -> 0 | E20: =SUMPRODUCT((Sales!$B$2:$B$50=7)*(MONTH(Sales!$G$2:$G$50)=3)*Sales!$F$2:$F$50) -> 4800 | F20: =SUMPRODUCT((Sales!$B$2:$B$50=7)*(MONTH(Sales!$G$2:$G$50)=4)*Sales!$F$2:$F$50) -> 0 | G20: =SUMPRODUCT((Sales!$B$2:$B$50=7)*(MONTH(Sales!$G$2:$G$50)=5)*Sales!$F$2:$F$50) -> 2400 | H20: =SUMPRODUCT((Sales!$B$2:$B$50=7)*(MONTH(Sales!$G$2:$G$50)=6)*Sales!$F$2:$F$50) -> 0
A21: 8 | B21: Nike Football Cleats | C21: =SUMPRODUCT((Sales!$B$2:$B$50=8)*(MONTH(Sales!$G$2:$G$50)=1)*Sales!$F$2:$F$50) -> 0 | D21: =SUMPRODUCT((Sales!$B$2:$B$50=8)*(MONTH(Sales!$G$2:$G$50)=2)*Sales!$F$2:$F$50) -> 5000 | E21: =SUMPRODUCT((Sales!$B$2:$B$50=8)*(MONTH(Sales!$G$2:$G$50)=3)*Sales!$F$2:$F$50) -> 0 | F21: =SUMPRODUCT((Sales!$B$2:$B$50=8)*(MONTH(Sales!$G$2:$G$50)=4)*Sales!$F$2:$F$50) -> 0 | G21: =SUMPRODUCT((Sales!$B$2:$B$50=8)*(MONTH(Sales!$G$2:$G$50)=5)*Sales!$F$2:$F$50) -> 2500 | H21: =SUMPRODUCT((Sales!$B$2:$B$50=8)*(MONTH(Sales!$G$2:$G$50)=6)*Sales!$F$2:$F$50) -> 0
A22: 9 | B22: Arena Swimsuit (Men) | C22: =SUMPRODUCT((Sales!$B$2:$B$50=9)*(MONTH(Sales!$G$2:$G$50)=1)*Sales!$F$2:$F$50) -> 0 | D22: =SUMPRODUCT((Sales!$B$2:$B$50=9)*(MONTH(Sales!$G$2:$G$50)=2)*Sales!$F$2:$F$50) -> 0 | E22: =SUMPRODUCT((Sales!$B$2:$B$50=9)*(MONTH(Sales!$G$2:$G$50)=3)*Sales!$F$2:$F$50) -> 0 | F22: =SUMPRODUCT((Sales!$B$2:$B$50=9)*(MONTH(Sales!$G$2:$G$50)=4)*Sales!$F$2:$F$50) -> 3600 | G22: =SUMPRODUCT((Sales!$B$2:$B$50=9)*(MONTH(Sales!$G$2:$G$50)=5)*Sales!$F$2:$F$50) -> 0 | H22: =SUMPRODUCT((Sales!$B$2:$B$50=9)*(MONTH(Sales!$G$2:$G$50)=6)*Sales!$F$2:$F$50) -> 0
A23: 10 | B23: Dumbbell Set 20 kg | C23: =SUMPRODUCT((Sales!$B$2:$B$50=10)*(MONTH(Sales!$G$2:$G$50)=1)*Sales!$F$2:$F$50) -> 0 | D23: =SUMPRODUCT((Sales!$B$2:$B$50=10)*(MONTH(Sales!$G$2:$G$50)=2)*Sales!$F$2:$F$50) -> 0 | E23: =SUMPRODUCT((Sales!$B$2:$B$50=10)*(MONTH(Sales!$G$2:$G$50)=3)*Sales!$F$2:$F$50) -> 18000 | F23: =SUMPRODUCT((Sales!$B$2:$B$50=10)*(MONTH(Sales!$G$2:$G$50)=4)*Sales!$F$2:$F$50) -> 0 | G23: =SUMPRODUCT((Sales!$B$2:$B$50=10)*(MONTH(Sales!$G$2:$G$50)=5)*Sales!$F$2:$F$50) -> 0 | H23: =SUMPRODUCT((Sales!$B$2:$B$50=10)*(MONTH(Sales!$G$2:$G$50)=6)*Sales!$F$2:$F$50) -> 9000
A26: 3) Total Purchases by Product Category
A27: Category | B27: Total_Cost
A28: Football | B28: =SUMIFS(Purchases!$F$2:$F$50,Purchases!$I$2:$I$50,"Football") -> 518500
A29: Gym | B29: =SUMIFS(Purchases!$F$2:$F$50,Purchases!$I$2:$I$50,"Gym") -> 464000
A30: Swimming | B30: =SUMIFS(Purchases!$F$2:$F$50,Purchases!$I$2:$I$50,"Swimming") -> 185500
A31: Running | B31: =SUMIFS(Purchases!$F$2:$F$50,Purchases!$I$2:$I$50,"Running") -> 444000
A32: Cycling | B32: =SUMIFS(Purchases!$F$2:$F$50,Purchases!$I$2:$I$50,"Cycling") -> 210000
A34: 4) Total Expenses by Month
A35: Month | B35: Total_Expenses
A36: M1 | B36: =SUMPRODUCT((MONTH(Expenses!$D$2:$D$50)=1)*Expenses!$C$2:$C$50) -> 41300
A37: M2 | B37: =SUMPRODUCT((MONTH(Expenses!$D$2:$D$50)=2)*Expenses!$C$2:$C$50) -> 42500
A38: M3 | B38: =SUMPRODUCT((MONTH(Expenses!$D$2:$D$50)=3)*Expenses!$C$2:$C$50) -> 39200
A39: M4 | B39: =SUMPRODUCT((MONTH(Expenses!$D$2:$D$50)=4)*Expenses!$C$2:$C$50) -> 0
A40: M5 | B40: =SUMPRODUCT((MONTH(Expenses!$D$2:$D$50)=5)*Expenses!$C$2:$C$50) -> 0
A41: M6 | B41: =SUMPRODUCT((MONTH(Expenses!$D$2:$D$50)=6)*Expenses!$C$2:$C$50) -> 0

Sheet Dashboard
A1: FitZone Sports — Business Dashboard
A3: Total Revenue | C3: Total Profit | E3: Avg Profit Margin
A4: =SUM(Sales!F2:F50) -> 332650 | C4: =SUM(Sales!N2:N50) -> 84935 | E4: =IFERROR(SUM(Sales!N2:N50)/SUM(Sales!F2:F50),0) -> 0.25532842
A6: Total Expenses | C6: Total Stock Value | E6: Total Remaining Stock
A7: =SUM(Expenses!C2:C50) -> 123000 | C7: =SUMPRODUCT(Product!D2:D11,Product!E2:E11) -> 1194100 | E7: =SUM(Analysis!E13:E22) -> 529
A10: Profit per Category | E10: Profit Share by Category
A29: Total Expenses Trend (by Month)
